package/__init__.py
package/main.py
why_is_the_singular_form_of_the_word_ears_not_ushu_but_ear/__init__.py
why_is_the_singular_form_of_the_word_ears_not_ushu_but_ear/main.py
why_is_the_singular_form_of_the_word_ears_not_ushu_but_ear-0.1.2.dist-info/METADATA
why_is_the_singular_form_of_the_word_ears_not_ushu_but_ear-0.1.2.dist-info/WHEEL
why_is_the_singular_form_of_the_word_ears_not_ushu_but_ear-0.1.2.dist-info/top_level.txt
why_is_the_singular_form_of_the_word_ears_not_ushu_but_ear-0.1.2.dist-info/RECORD
