Metadata-Version: 2.1
Name: why-is-the-singular-form-of-the-word-ears-not-ushu-but-ear
Version: 0.1.2
Summary: Mem modul
Author: Nodus
Classifier: Programming Language :: Python :: 3.11
Classifier: License :: OSI Approved :: MIT License
Classifier: Operating System :: OS Independent
Requires-Python: >=3.11
